main.py
orats_py-0.1.0.dist-info/METADATA
orats_py-0.1.0.dist-info/WHEEL
orats_py-0.1.0.dist-info/top_level.txt
orats_py-0.1.0.dist-info/RECORD
