Metadata-Version: 2.4
Name: orats-py
Version: 0.1.0
Summary: ORATS Client SDK
Requires-Python: >=3.14
